odoo/addons/mrp_stock_owner_restriction/README.rst
odoo/addons/mrp_stock_owner_restriction/__init__.py
odoo/addons/mrp_stock_owner_restriction/__manifest__.py
odoo/addons/mrp_stock_owner_restriction/i18n/it.po
odoo/addons/mrp_stock_owner_restriction/i18n/ja.po
odoo/addons/mrp_stock_owner_restriction/i18n/mrp_stock_owner_restriction.pot
odoo/addons/mrp_stock_owner_restriction/i18n/nl.po
odoo/addons/mrp_stock_owner_restriction/models/__init__.py
odoo/addons/mrp_stock_owner_restriction/models/mrp_production.py
odoo/addons/mrp_stock_owner_restriction/models/mrp_unbuild.py
odoo/addons/mrp_stock_owner_restriction/models/stock_move.py
odoo/addons/mrp_stock_owner_restriction/models/stock_move_line.py
odoo/addons/mrp_stock_owner_restriction/readme/CONTRIBUTORS.rst
odoo/addons/mrp_stock_owner_restriction/readme/DESCRIPTION.rst
odoo/addons/mrp_stock_owner_restriction/readme/ROADMAP.rst
odoo/addons/mrp_stock_owner_restriction/static/description/icon.png
odoo/addons/mrp_stock_owner_restriction/static/description/index.html
odoo/addons/mrp_stock_owner_restriction/tests/__init__.py
odoo/addons/mrp_stock_owner_restriction/tests/test_mrp_stock_owner_restriction.py
odoo/addons/mrp_stock_owner_restriction/views/mrp_production_views.xml
odoo_addon_mrp_stock_owner_restriction-16.0.1.0.1.dist-info/METADATA
odoo_addon_mrp_stock_owner_restriction-16.0.1.0.1.dist-info/WHEEL
odoo_addon_mrp_stock_owner_restriction-16.0.1.0.1.dist-info/top_level.txt
odoo_addon_mrp_stock_owner_restriction-16.0.1.0.1.dist-info/RECORD
